vsmidas/__init__.py
vsmidas/__main__.py
vsmidas/base_model.py
vsmidas/blocks.py
vsmidas/dpt_depth.py
vsmidas/backbones/beit.py
vsmidas/backbones/levit.py
vsmidas/backbones/next_vit.py
vsmidas/backbones/swin.py
vsmidas/backbones/swin2.py
vsmidas/backbones/swin_common.py
vsmidas/backbones/utils.py
vsmidas/backbones/vit.py
vsmidas/models/dpt_beit_large_512.pt
vsmidas/models/dpt_large_384.pt
vsmidas/models/dpt_swin2_large_384.pt
vsmidas/models/dpt_swin2_tiny_256.pt
vsmidas-1.1.0.dist-info/METADATA
vsmidas-1.1.0.dist-info/WHEEL
vsmidas-1.1.0.dist-info/licenses/LICENSE
vsmidas-1.1.0.dist-info/RECORD
