Metadata-Version: 2.1
Name: vsmidas
Version: 1.1.0
Summary: MiDaS function for VapourSynth
Project-URL: Homepage, https://github.com/HolyWu/vs-midas
Project-URL: Bug Tracker, https://github.com/HolyWu/vs-midas/issues
Author-email: HolyWu <holywu@gmail.com>
License: MIT License
License-File: LICENSE
Keywords: MiDaS,VapourSynth
Classifier: License :: OSI Approved :: MIT License
Classifier: Operating System :: OS Independent
Classifier: Programming Language :: Python :: 3 :: Only
Classifier: Topic :: Multimedia :: Video
Requires-Python: >=3.11
Requires-Dist: numpy>=1.26.2
Requires-Dist: opencv-python>=4.8.1.78
Requires-Dist: requests>=2.31.0
Requires-Dist: timm==0.6.13
Requires-Dist: torch>=2.1.0
Requires-Dist: torchvision>=0.16.0
Requires-Dist: tqdm>=4.66.1
Requires-Dist: vapoursynth>=62
